tabdoc/__init__.py
tabdoc/tabexcel.py
tabdoc/tabpdf.py
tabdoc/tabword.py
tabdoc/templates/SimHei.ttf
tabdoc/templates/__init__.py
tabdoc/templates/template.docx
tabdoc-1.1.0.dist-info/LICENSE
tabdoc-1.1.0.dist-info/METADATA
tabdoc-1.1.0.dist-info/WHEEL
tabdoc-1.1.0.dist-info/top_level.txt
tabdoc-1.1.0.dist-info/RECORD
